bm_data_eng/bigquery.py
bm_data_eng/s3_to_gcs.py
bm_data_eng/transform.py
bm_data_eng/wrappers.py
bm_data_eng-1.1.0.dist-info/METADATA
bm_data_eng-1.1.0.dist-info/WHEEL
bm_data_eng-1.1.0.dist-info/top_level.txt
bm_data_eng-1.1.0.dist-info/RECORD
