Metadata-Version: 2.1
Name: bm-data-eng
Version: 1.1.0
Summary: BM Data Eng lib to transfer files from S3 to GCS, transform them and load them to BQ
Home-page: UNKNOWN
Author: Thomas Pilewicz
Author-email: UNKNOWN
License: UNKNOWN
Platform: UNKNOWN
Requires-Dist: pandas (==1.1.5)
Requires-Dist: pyarrow (==4.0.1)
